kw_nlp100/__init__.py
kw_nlp100/display.py
kw_nlp100/gdrive.py
kw_nlp100/kw_nlp100.py
kw_nlp100-0.0.6.dist-info/LICENSE.txt
kw_nlp100-0.0.6.dist-info/METADATA
kw_nlp100-0.0.6.dist-info/WHEEL
kw_nlp100-0.0.6.dist-info/top_level.txt
kw_nlp100-0.0.6.dist-info/RECORD
