Metadata-Version: 2.1
Name: kw-nlp100
Version: 0.0.6
Summary: Ken's convenience tool for pursuit of "NLP100 knock challenge"
Author: Ken Wakita
Author-email: wakita@is.titech.ac.jp
Classifier: Programming Language :: Python :: 3
Classifier: License :: OSI Approved :: MIT License
Classifier: Operating System :: OS Independent
Requires-Python: >=3.7
License-File: LICENSE.txt
